{
   "request": [
       {
           "id": 1,
           "titulo": "Puerta Inteligente",
           "imagen": "url_de_imagen_principal",
           "descripcion": "Puerta inteligente con Wifi y NFC.",
           "color": "CardColor",
           "precio": 500,
           "imagen1": "url_de_imagen_1",
           "imagen2": "url_de_imagen_2",
           "imagen3": "url_de_imagen_3",
           "video": "url_de_video",
           "mainCard": true
       },
       {
           "id": 2,
           "titulo": "Puerta Inteligente2",
           "imagen": "url_de_imagen_principal",
           "descripcion": "Puerta inteligente con Wifi y NFC.",
           "color": "CardColor",
           "precio": 500,
           "imagen1": "url_de_imagen_1",
           "imagen2": "url_de_imagen_2",
           "imagen3": "url_de_imagen_3",
           "video": "url_de_video",
           "mainCard": true
       },
       {
           "id": 3,
           "titulo": "Bombilla inteligente",
           "imagen": "url_de_imagen_principal",
           "descripcion": "Bombilla con wifi que se enciende a distancia",
           "color": "SubCardColor",
           "precio": 500,
           "imagen1": "url_de_imagen_1",
           "imagen2": "url_de_imagen_2",
           "imagen3": "url_de_imagen_3",
           "video": "url_de_video",
           "mainCard": false
       },
       {
           "id": 4,
           "titulo": "enchufe inteligente",
           "imagen": "url_de_imagen_principal",
           "descripcion": "enchufe con wifi que se enciende a distancia",
           "color": "SubCardColor",
           "precio": 500,
           "imagen1": "url_de_imagen_1",
           "imagen2": "url_de_imagen_2",
           "imagen3": "url_de_imagen_3",
           "video": "url_de_video",
           "mainCard": false
       }
   ]
}
